hactool/__init__.py
hactool/pyp.py
hactool/module/pick.py
hactool/module/tabulate.py
hactool0-0.15.0.dist-info/LICENSE
hactool0-0.15.0.dist-info/METADATA
hactool0-0.15.0.dist-info/WHEEL
hactool0-0.15.0.dist-info/top_level.txt
hactool0-0.15.0.dist-info/RECORD
