Metadata-Version: 2.1
Name: hactool0
Version: 0.15.0
Summary: This tool can help you a lot
Home-page: 
Author: GhostShadow
License: GNU
Keywords: hactool,pyp
License-File: LICENSE
Requires-Dist: keyboard
Requires-Dist: pyperclip
